LICENSE.txt
MANIFEST.in
README.rst
setup.py
aldryn_locations/__init__.py
aldryn_locations/cms_plugins.py
aldryn_locations/forms.py
aldryn_locations/models.py
aldryn_locations.egg-info/PKG-INFO
aldryn_locations.egg-info/SOURCES.txt
aldryn_locations.egg-info/dependency_links.txt
aldryn_locations.egg-info/not-zip-safe
aldryn_locations.egg-info/top_level.txt
aldryn_locations/boilerplates/bootstrap3/static/js/addons/cl.locations.js
aldryn_locations/boilerplates/bootstrap3/static/js/addons/cl.locations.min.js
aldryn_locations/boilerplates/bootstrap3/static/js/libs/class.min.js
aldryn_locations/boilerplates/bootstrap3/templates/aldryn_locations/plugins/empty.html
aldryn_locations/boilerplates/bootstrap3/templates/aldryn_locations/plugins/locations.html
aldryn_locations/boilerplates/bootstrap3/templates/aldryn_locations/plugins/locations_embed.html
aldryn_locations/boilerplates/legacy/static/js/addons/cl.locations.js
aldryn_locations/boilerplates/legacy/static/js/libs/class.min.js
aldryn_locations/boilerplates/legacy/templates/aldryn_locations/plugins/empty.html
aldryn_locations/boilerplates/legacy/templates/aldryn_locations/plugins/locations.html
aldryn_locations/boilerplates/legacy/templates/aldryn_locations/plugins/locations_embed.html
aldryn_locations/locale/de/LC_MESSAGES/django.mo
aldryn_locations/locale/de/LC_MESSAGES/django.po
aldryn_locations/locale/en/LC_MESSAGES/django.mo
aldryn_locations/locale/en/LC_MESSAGES/django.po
aldryn_locations/locale/es/LC_MESSAGES/django.mo
aldryn_locations/locale/es/LC_MESSAGES/django.po
aldryn_locations/locale/fr/LC_MESSAGES/django.mo
aldryn_locations/locale/fr/LC_MESSAGES/django.po
aldryn_locations/locale/it/LC_MESSAGES/django.mo
aldryn_locations/locale/it/LC_MESSAGES/django.po
aldryn_locations/migrations/0001_initial.py
aldryn_locations/migrations/__init__.py
aldryn_locations/south_migrations/0001_initial.py
aldryn_locations/south_migrations/0002_auto__chg_field_locationplugin_lat__chg_field_locationplugin_lng.py
aldryn_locations/south_migrations/0003_auto__add_embedplaceplugin__add_embedviewplugin__add_embeddirectionspl.py
aldryn_locations/south_migrations/__init__.py
